lib/__init__.py
tests/__init__.py
tests/test_lib.py
anurag_simplecalculator-0.0.3.dist-info/LICENCE
anurag_simplecalculator-0.0.3.dist-info/METADATA
anurag_simplecalculator-0.0.3.dist-info/WHEEL
anurag_simplecalculator-0.0.3.dist-info/top_level.txt
anurag_simplecalculator-0.0.3.dist-info/RECORD
