Metadata-Version: 2.1
Name: anurag-simplecalculator
Version: 0.0.3
Summary: A very basic calculator
Home-page: https://github.com/anuragpatil94/simplecalculator
Author: Anurag Patil
Author-email: UNKNOWN
License: MIT
Keywords: calculator,educative,example
Platform: UNKNOWN
Classifier: Development Status :: 5 - Production/Stable
Classifier: Intended Audience :: Education
Classifier: Operating System :: Microsoft :: Windows :: Windows 10
Classifier: License :: OSI Approved :: MIT License
Classifier: Programming Language :: Python :: 3
